devion_test/__init__.py
devion_test-0.0.1.dist-info/licenses/LICENSE
devion_test-0.0.1.dist-info/METADATA
devion_test-0.0.1.dist-info/WHEEL
devion_test-0.0.1.dist-info/top_level.txt
devion_test-0.0.1.dist-info/RECORD
