Metadata-Version: 2.4
Name: devion_test
Version: 0.0.1
Summary: Test package for Devion workflow
Home-page: https://github.com/MattHeeper/Devion
Author: MattHeeper
License: Apache-2.0
Requires-Python: >=3.11
License-File: LICENSE
Dynamic: author
Dynamic: description
Dynamic: description-content-type
Dynamic: home-page
Dynamic: license
Dynamic: license-file
Dynamic: requires-python
Dynamic: summary
